ignorio/__init__.py
ignorio/cli.py
ignorio/ignorio.py
ignorio-0.2.4.dist-info/entry_points.txt
ignorio-0.2.4.dist-info/LICENSE.md
ignorio-0.2.4.dist-info/WHEEL
ignorio-0.2.4.dist-info/METADATA
ignorio-0.2.4.dist-info/RECORD
